zdpapi/__init__.py
zdpapi/api/__init__.py
zdpapi/api/api_.py
zdpapi/libs/__init__.py
zdpapi/libs/fastapi/__init__.py
zdpapi/libs/fastapi/applications.py
zdpapi/libs/fastapi/background.py
zdpapi/libs/fastapi/concurrency.py
zdpapi/libs/fastapi/datastructures.py
zdpapi/libs/fastapi/dependencies/__init__.py
zdpapi/libs/fastapi/dependencies/models.py
zdpapi/libs/fastapi/dependencies/utils.py
zdpapi/libs/fastapi/encoders.py
zdpapi/libs/fastapi/exception_handlers.py
zdpapi/libs/fastapi/exceptions.py
zdpapi/libs/fastapi/logger.py
zdpapi/libs/fastapi/middleware/__init__.py
zdpapi/libs/fastapi/middleware/cors.py
zdpapi/libs/fastapi/middleware/gzip.py
zdpapi/libs/fastapi/middleware/httpsredirect.py
zdpapi/libs/fastapi/middleware/trustedhost.py
zdpapi/libs/fastapi/middleware/wsgi.py
zdpapi/libs/fastapi/openapi/__init__.py
zdpapi/libs/fastapi/openapi/constants.py
zdpapi/libs/fastapi/openapi/docs.py
zdpapi/libs/fastapi/openapi/models.py
zdpapi/libs/fastapi/openapi/utils.py
zdpapi/libs/fastapi/param_functions.py
zdpapi/libs/fastapi/params.py
zdpapi/libs/fastapi/plugins.py
zdpapi/libs/fastapi/py.typed
zdpapi/libs/fastapi/requests.py
zdpapi/libs/fastapi/responses.py
zdpapi/libs/fastapi/routing.py
zdpapi/libs/fastapi/security/__init__.py
zdpapi/libs/fastapi/security/api_key.py
zdpapi/libs/fastapi/security/base.py
zdpapi/libs/fastapi/security/http.py
zdpapi/libs/fastapi/security/oauth2.py
zdpapi/libs/fastapi/security/open_id_connect_url.py
zdpapi/libs/fastapi/security/utils.py
zdpapi/libs/fastapi/staticfiles.py
zdpapi/libs/fastapi/templating.py
zdpapi/libs/fastapi/testclient.py
zdpapi/libs/fastapi/types.py
zdpapi/libs/fastapi/utils.py
zdpapi/libs/fastapi/websockets.py
zdpapi/libs/starlette/__init__.py
zdpapi/libs/starlette/applications.py
zdpapi/libs/starlette/authentication.py
zdpapi/libs/starlette/background.py
zdpapi/libs/starlette/concurrency.py
zdpapi/libs/starlette/config.py
zdpapi/libs/starlette/convertors.py
zdpapi/libs/starlette/datastructures.py
zdpapi-0.1.0.dist-info/LICENSE
zdpapi-0.1.0.dist-info/WHEEL
zdpapi-0.1.0.dist-info/METADATA
zdpapi-0.1.0.dist-info/RECORD
